[
    {
        "id":  25897163755,
        "node_id":  "ME_lADOSVlrQ88AAAABDOPQBc8AAAAGB5db6w",
        "url":  "https://api.github.com/repos/RustCADs/RGE/issues/events/25897163755",
        "actor":  {
                      "login":  "drhalilmurattasci",
                      "id":  226582914,
                      "node_id":  "U_kgDODYFhgg",
                      "avatar_url":  "https://avatars.githubusercontent.com/u/226582914?v=4",
                      "gravatar_id":  "",
                      "url":  "https://api.github.com/users/drhalilmurattasci",
                      "html_url":  "https://github.com/drhalilmurattasci",
                      "followers_url":  "https://api.github.com/users/drhalilmurattasci/followers",
                      "following_url":  "https://api.github.com/users/drhalilmurattasci/following{/other_user}",
                      "gists_url":  "https://api.github.com/users/drhalilmurattasci/gists{/gist_id}",
                      "starred_url":  "https://api.github.com/users/drhalilmurattasci/starred{/owner}{/repo}",
                      "subscriptions_url":  "https://api.github.com/users/drhalilmurattasci/subscriptions",
                      "organizations_url":  "https://api.github.com/users/drhalilmurattasci/orgs",
                      "repos_url":  "https://api.github.com/users/drhalilmurattasci/repos",
                      "events_url":  "https://api.github.com/users/drhalilmurattasci/events{/privacy}",
                      "received_events_url":  "https://api.github.com/users/drhalilmurattasci/received_events",
                      "type":  "User",
                      "user_view_type":  "public",
                      "site_admin":  false
                  },
        "event":  "merged",
        "commit_id":  "2035a002014bf5fb62d5aa97e0932af4a98fc2c3",
        "commit_url":  "https://api.github.com/repos/RustCADs/RGE/commits/2035a002014bf5fb62d5aa97e0932af4a98fc2c3",
        "created_at":  "2026-05-24T10:38:09Z",
        "performed_via_github_app":  null
    },
    {
        "id":  25897163766,
        "node_id":  "CE_lADOSVlrQ88AAAABDOPQBc8AAAAGB5db9g",
        "url":  "https://api.github.com/repos/RustCADs/RGE/issues/events/25897163766",
        "actor":  {
                      "login":  "drhalilmurattasci",
                      "id":  226582914,
                      "node_id":  "U_kgDODYFhgg",
                      "avatar_url":  "https://avatars.githubusercontent.com/u/226582914?v=4",
                      "gravatar_id":  "",
                      "url":  "https://api.github.com/users/drhalilmurattasci",
                      "html_url":  "https://github.com/drhalilmurattasci",
                      "followers_url":  "https://api.github.com/users/drhalilmurattasci/followers",
                      "following_url":  "https://api.github.com/users/drhalilmurattasci/following{/other_user}",
                      "gists_url":  "https://api.github.com/users/drhalilmurattasci/gists{/gist_id}",
                      "starred_url":  "https://api.github.com/users/drhalilmurattasci/starred{/owner}{/repo}",
                      "subscriptions_url":  "https://api.github.com/users/drhalilmurattasci/subscriptions",
                      "organizations_url":  "https://api.github.com/users/drhalilmurattasci/orgs",
                      "repos_url":  "https://api.github.com/users/drhalilmurattasci/repos",
                      "events_url":  "https://api.github.com/users/drhalilmurattasci/events{/privacy}",
                      "received_events_url":  "https://api.github.com/users/drhalilmurattasci/received_events",
                      "type":  "User",
                      "user_view_type":  "public",
                      "site_admin":  false
                  },
        "event":  "closed",
        "commit_id":  null,
        "commit_url":  null,
        "created_at":  "2026-05-24T10:38:09Z",
        "state_reason":  null,
        "performed_via_github_app":  null
    },
    {
        "id":  25897164095,
        "node_id":  "HRDE_lADOSVlrQ88AAAABDOPQBc8AAAAGB5ddPw",
        "url":  "https://api.github.com/repos/RustCADs/RGE/issues/events/25897164095",
        "actor":  {
                      "login":  "drhalilmurattasci",
                      "id":  226582914,
                      "node_id":  "U_kgDODYFhgg",
                      "avatar_url":  "https://avatars.githubusercontent.com/u/226582914?v=4",
                      "gravatar_id":  "",
                      "url":  "https://api.github.com/users/drhalilmurattasci",
                      "html_url":  "https://github.com/drhalilmurattasci",
                      "followers_url":  "https://api.github.com/users/drhalilmurattasci/followers",
                      "following_url":  "https://api.github.com/users/drhalilmurattasci/following{/other_user}",
                      "gists_url":  "https://api.github.com/users/drhalilmurattasci/gists{/gist_id}",
                      "starred_url":  "https://api.github.com/users/drhalilmurattasci/starred{/owner}{/repo}",
                      "subscriptions_url":  "https://api.github.com/users/drhalilmurattasci/subscriptions",
                      "organizations_url":  "https://api.github.com/users/drhalilmurattasci/orgs",
                      "repos_url":  "https://api.github.com/users/drhalilmurattasci/repos",
                      "events_url":  "https://api.github.com/users/drhalilmurattasci/events{/privacy}",
                      "received_events_url":  "https://api.github.com/users/drhalilmurattasci/received_events",
                      "type":  "User",
                      "user_view_type":  "public",
                      "site_admin":  false
                  },
        "event":  "head_ref_deleted",
        "commit_id":  null,
        "commit_url":  null,
        "created_at":  "2026-05-24T10:38:11Z",
        "performed_via_github_app":  null
    }
]
