[
    {
        "id":  26751919323,
        "node_id":  "LE_lADOSVlrQ88AAAABFgH2k88AAAAGOonk2w",
        "url":  "https://api.github.com/repos/RustCADs/RGE/issues/events/26751919323",
        "actor":  {
                      "login":  "drhalilmurattasci",
                      "id":  226582914,
                      "node_id":  "U_kgDODYFhgg",
                      "avatar_url":  "https://avatars.githubusercontent.com/u/226582914?v=4",
                      "gravatar_id":  "",
                      "url":  "https://api.github.com/users/drhalilmurattasci",
                      "html_url":  "https://github.com/drhalilmurattasci",
                      "followers_url":  "https://api.github.com/users/drhalilmurattasci/followers",
                      "following_url":  "https://api.github.com/users/drhalilmurattasci/following{/other_user}",
                      "gists_url":  "https://api.github.com/users/drhalilmurattasci/gists{/gist_id}",
                      "starred_url":  "https://api.github.com/users/drhalilmurattasci/starred{/owner}{/repo}",
                      "subscriptions_url":  "https://api.github.com/users/drhalilmurattasci/subscriptions",
                      "organizations_url":  "https://api.github.com/users/drhalilmurattasci/orgs",
                      "repos_url":  "https://api.github.com/users/drhalilmurattasci/repos",
                      "events_url":  "https://api.github.com/users/drhalilmurattasci/events{/privacy}",
                      "received_events_url":  "https://api.github.com/users/drhalilmurattasci/received_events",
                      "type":  "User",
                      "user_view_type":  "public",
                      "site_admin":  false
                  },
        "event":  "labeled",
        "commit_id":  null,
        "commit_url":  null,
        "created_at":  "2026-06-15T10:23:31Z",
        "label":  {
                      "name":  "ai-dispatch",
                      "color":  "0e8a16"
                  },
        "performed_via_github_app":  null
    },
    {
        "id":  26751919536,
        "node_id":  "LE_lADOSVlrQ88AAAABFgH2k88AAAAGOonlsA",
        "url":  "https://api.github.com/repos/RustCADs/RGE/issues/events/26751919536",
        "actor":  {
                      "login":  "drhalilmurattasci",
                      "id":  226582914,
                      "node_id":  "U_kgDODYFhgg",
                      "avatar_url":  "https://avatars.githubusercontent.com/u/226582914?v=4",
                      "gravatar_id":  "",
                      "url":  "https://api.github.com/users/drhalilmurattasci",
                      "html_url":  "https://github.com/drhalilmurattasci",
                      "followers_url":  "https://api.github.com/users/drhalilmurattasci/followers",
                      "following_url":  "https://api.github.com/users/drhalilmurattasci/following{/other_user}",
                      "gists_url":  "https://api.github.com/users/drhalilmurattasci/gists{/gist_id}",
                      "starred_url":  "https://api.github.com/users/drhalilmurattasci/starred{/owner}{/repo}",
                      "subscriptions_url":  "https://api.github.com/users/drhalilmurattasci/subscriptions",
                      "organizations_url":  "https://api.github.com/users/drhalilmurattasci/orgs",
                      "repos_url":  "https://api.github.com/users/drhalilmurattasci/repos",
                      "events_url":  "https://api.github.com/users/drhalilmurattasci/events{/privacy}",
                      "received_events_url":  "https://api.github.com/users/drhalilmurattasci/received_events",
                      "type":  "User",
                      "user_view_type":  "public",
                      "site_admin":  false
                  },
        "event":  "labeled",
        "commit_id":  null,
        "commit_url":  null,
        "created_at":  "2026-06-15T10:23:32Z",
        "label":  {
                      "name":  "ai-auto",
                      "color":  "1d76db"
                  },
        "performed_via_github_app":  null
    },
    {
        "id":  26751931995,
        "node_id":  "LE_lADOSVlrQ88AAAABFgH2k88AAAAGOooWWw",
        "url":  "https://api.github.com/repos/RustCADs/RGE/issues/events/26751931995",
        "actor":  {
                      "login":  "drhalilmurattasci",
                      "id":  226582914,
                      "node_id":  "U_kgDODYFhgg",
                      "avatar_url":  "https://avatars.githubusercontent.com/u/226582914?v=4",
                      "gravatar_id":  "",
                      "url":  "https://api.github.com/users/drhalilmurattasci",
                      "html_url":  "https://github.com/drhalilmurattasci",
                      "followers_url":  "https://api.github.com/users/drhalilmurattasci/followers",
                      "following_url":  "https://api.github.com/users/drhalilmurattasci/following{/other_user}",
                      "gists_url":  "https://api.github.com/users/drhalilmurattasci/gists{/gist_id}",
                      "starred_url":  "https://api.github.com/users/drhalilmurattasci/starred{/owner}{/repo}",
                      "subscriptions_url":  "https://api.github.com/users/drhalilmurattasci/subscriptions",
                      "organizations_url":  "https://api.github.com/users/drhalilmurattasci/orgs",
                      "repos_url":  "https://api.github.com/users/drhalilmurattasci/repos",
                      "events_url":  "https://api.github.com/users/drhalilmurattasci/events{/privacy}",
                      "received_events_url":  "https://api.github.com/users/drhalilmurattasci/received_events",
                      "type":  "User",
                      "user_view_type":  "public",
                      "site_admin":  false
                  },
        "event":  "labeled",
        "commit_id":  null,
        "commit_url":  null,
        "created_at":  "2026-06-15T10:23:50Z",
        "label":  {
                      "name":  "ai-dispatch-running",
                      "color":  "fbca04"
                  },
        "performed_via_github_app":  null
    },
    {
        "id":  26753941269,
        "node_id":  "REFE_lADOSVlrQ88AAAABFgH2k88AAAAGOqi_FQ",
        "url":  "https://api.github.com/repos/RustCADs/RGE/issues/events/26753941269",
        "actor":  {
                      "login":  "drhalilmurattasci",
                      "id":  226582914,
                      "node_id":  "U_kgDODYFhgg",
                      "avatar_url":  "https://avatars.githubusercontent.com/u/226582914?v=4",
                      "gravatar_id":  "",
                      "url":  "https://api.github.com/users/drhalilmurattasci",
                      "html_url":  "https://github.com/drhalilmurattasci",
                      "followers_url":  "https://api.github.com/users/drhalilmurattasci/followers",
                      "following_url":  "https://api.github.com/users/drhalilmurattasci/following{/other_user}",
                      "gists_url":  "https://api.github.com/users/drhalilmurattasci/gists{/gist_id}",
                      "starred_url":  "https://api.github.com/users/drhalilmurattasci/starred{/owner}{/repo}",
                      "subscriptions_url":  "https://api.github.com/users/drhalilmurattasci/subscriptions",
                      "organizations_url":  "https://api.github.com/users/drhalilmurattasci/orgs",
                      "repos_url":  "https://api.github.com/users/drhalilmurattasci/repos",
                      "events_url":  "https://api.github.com/users/drhalilmurattasci/events{/privacy}",
                      "received_events_url":  "https://api.github.com/users/drhalilmurattasci/received_events",
                      "type":  "User",
                      "user_view_type":  "public",
                      "site_admin":  false
                  },
        "event":  "referenced",
        "commit_id":  "09cb2ae19d9f0ab8b2a370b2193a25bd9130392f",
        "commit_url":  "https://api.github.com/repos/RustCADs/RGE/commits/09cb2ae19d9f0ab8b2a370b2193a25bd9130392f",
        "created_at":  "2026-06-15T11:15:22Z",
        "performed_via_github_app":  null
    },
    {
        "id":  26753959897,
        "node_id":  "UNLE_lADOSVlrQ88AAAABFgH2k88AAAAGOqkH2Q",
        "url":  "https://api.github.com/repos/RustCADs/RGE/issues/events/26753959897",
        "actor":  {
                      "login":  "drhalilmurattasci",
                      "id":  226582914,
                      "node_id":  "U_kgDODYFhgg",
                      "avatar_url":  "https://avatars.githubusercontent.com/u/226582914?v=4",
                      "gravatar_id":  "",
                      "url":  "https://api.github.com/users/drhalilmurattasci",
                      "html_url":  "https://github.com/drhalilmurattasci",
                      "followers_url":  "https://api.github.com/users/drhalilmurattasci/followers",
                      "following_url":  "https://api.github.com/users/drhalilmurattasci/following{/other_user}",
                      "gists_url":  "https://api.github.com/users/drhalilmurattasci/gists{/gist_id}",
                      "starred_url":  "https://api.github.com/users/drhalilmurattasci/starred{/owner}{/repo}",
                      "subscriptions_url":  "https://api.github.com/users/drhalilmurattasci/subscriptions",
                      "organizations_url":  "https://api.github.com/users/drhalilmurattasci/orgs",
                      "repos_url":  "https://api.github.com/users/drhalilmurattasci/repos",
                      "events_url":  "https://api.github.com/users/drhalilmurattasci/events{/privacy}",
                      "received_events_url":  "https://api.github.com/users/drhalilmurattasci/received_events",
                      "type":  "User",
                      "user_view_type":  "public",
                      "site_admin":  false
                  },
        "event":  "unlabeled",
        "commit_id":  null,
        "commit_url":  null,
        "created_at":  "2026-06-15T11:15:51Z",
        "label":  {
                      "name":  "ai-dispatch",
                      "color":  "0e8a16"
                  },
        "performed_via_github_app":  null
    },
    {
        "id":  26753959908,
        "node_id":  "LE_lADOSVlrQ88AAAABFgH2k88AAAAGOqkH5A",
        "url":  "https://api.github.com/repos/RustCADs/RGE/issues/events/26753959908",
        "actor":  {
                      "login":  "drhalilmurattasci",
                      "id":  226582914,
                      "node_id":  "U_kgDODYFhgg",
                      "avatar_url":  "https://avatars.githubusercontent.com/u/226582914?v=4",
                      "gravatar_id":  "",
                      "url":  "https://api.github.com/users/drhalilmurattasci",
                      "html_url":  "https://github.com/drhalilmurattasci",
                      "followers_url":  "https://api.github.com/users/drhalilmurattasci/followers",
                      "following_url":  "https://api.github.com/users/drhalilmurattasci/following{/other_user}",
                      "gists_url":  "https://api.github.com/users/drhalilmurattasci/gists{/gist_id}",
                      "starred_url":  "https://api.github.com/users/drhalilmurattasci/starred{/owner}{/repo}",
                      "subscriptions_url":  "https://api.github.com/users/drhalilmurattasci/subscriptions",
                      "organizations_url":  "https://api.github.com/users/drhalilmurattasci/orgs",
                      "repos_url":  "https://api.github.com/users/drhalilmurattasci/repos",
                      "events_url":  "https://api.github.com/users/drhalilmurattasci/events{/privacy}",
                      "received_events_url":  "https://api.github.com/users/drhalilmurattasci/received_events",
                      "type":  "User",
                      "user_view_type":  "public",
                      "site_admin":  false
                  },
        "event":  "labeled",
        "commit_id":  null,
        "commit_url":  null,
        "created_at":  "2026-06-15T11:15:51Z",
        "label":  {
                      "name":  "ai-dispatch-done",
                      "color":  "5319e7"
                  },
        "performed_via_github_app":  null
    },
    {
        "id":  26753959920,
        "node_id":  "UNLE_lADOSVlrQ88AAAABFgH2k88AAAAGOqkH8A",
        "url":  "https://api.github.com/repos/RustCADs/RGE/issues/events/26753959920",
        "actor":  {
                      "login":  "drhalilmurattasci",
                      "id":  226582914,
                      "node_id":  "U_kgDODYFhgg",
                      "avatar_url":  "https://avatars.githubusercontent.com/u/226582914?v=4",
                      "gravatar_id":  "",
                      "url":  "https://api.github.com/users/drhalilmurattasci",
                      "html_url":  "https://github.com/drhalilmurattasci",
                      "followers_url":  "https://api.github.com/users/drhalilmurattasci/followers",
                      "following_url":  "https://api.github.com/users/drhalilmurattasci/following{/other_user}",
                      "gists_url":  "https://api.github.com/users/drhalilmurattasci/gists{/gist_id}",
                      "starred_url":  "https://api.github.com/users/drhalilmurattasci/starred{/owner}{/repo}",
                      "subscriptions_url":  "https://api.github.com/users/drhalilmurattasci/subscriptions",
                      "organizations_url":  "https://api.github.com/users/drhalilmurattasci/orgs",
                      "repos_url":  "https://api.github.com/users/drhalilmurattasci/repos",
                      "events_url":  "https://api.github.com/users/drhalilmurattasci/events{/privacy}",
                      "received_events_url":  "https://api.github.com/users/drhalilmurattasci/received_events",
                      "type":  "User",
                      "user_view_type":  "public",
                      "site_admin":  false
                  },
        "event":  "unlabeled",
        "commit_id":  null,
        "commit_url":  null,
        "created_at":  "2026-06-15T11:15:51Z",
        "label":  {
                      "name":  "ai-dispatch-running",
                      "color":  "fbca04"
                  },
        "performed_via_github_app":  null
    },
    {
        "id":  26753961906,
        "node_id":  "CE_lADOSVlrQ88AAAABFgH2k88AAAAGOqkPsg",
        "url":  "https://api.github.com/repos/RustCADs/RGE/issues/events/26753961906",
        "actor":  {
                      "login":  "drhalilmurattasci",
                      "id":  226582914,
                      "node_id":  "U_kgDODYFhgg",
                      "avatar_url":  "https://avatars.githubusercontent.com/u/226582914?v=4",
                      "gravatar_id":  "",
                      "url":  "https://api.github.com/users/drhalilmurattasci",
                      "html_url":  "https://github.com/drhalilmurattasci",
                      "followers_url":  "https://api.github.com/users/drhalilmurattasci/followers",
                      "following_url":  "https://api.github.com/users/drhalilmurattasci/following{/other_user}",
                      "gists_url":  "https://api.github.com/users/drhalilmurattasci/gists{/gist_id}",
                      "starred_url":  "https://api.github.com/users/drhalilmurattasci/starred{/owner}{/repo}",
                      "subscriptions_url":  "https://api.github.com/users/drhalilmurattasci/subscriptions",
                      "organizations_url":  "https://api.github.com/users/drhalilmurattasci/orgs",
                      "repos_url":  "https://api.github.com/users/drhalilmurattasci/repos",
                      "events_url":  "https://api.github.com/users/drhalilmurattasci/events{/privacy}",
                      "received_events_url":  "https://api.github.com/users/drhalilmurattasci/received_events",
                      "type":  "User",
                      "user_view_type":  "public",
                      "site_admin":  false
                  },
        "event":  "closed",
        "commit_id":  null,
        "commit_url":  null,
        "created_at":  "2026-06-15T11:15:54Z",
        "state_reason":  null,
        "performed_via_github_app":  null
    }
]
